abstract_ocr/__init__.py
abstract_ocr/imports/__init__.py
abstract_ocr/imports/functions.py
abstract_ocr/imports/imports.py
abstract_ocr/imports/image_utils/__init__.py
abstract_ocr/imports/image_utils/cv_constants.py
abstract_ocr/imports/image_utils/image_readers.py
abstract_ocr/imports/image_utils/threshold_utils.py
abstract_ocr/ocr_utils/__init__.py
abstract_ocr/ocr_utils/column_utils.py
abstract_ocr/ocr_utils/getimg.py
abstract_ocr/ocr_utils/imports.py
abstract_ocr/ocr_utils/layered_ocr.py
abstract_ocr/ocr_utils/paddle_manager.py
abstract_ocr/old/__init__.py
abstract_ocr/old/imports.py
abstract_ocr/old/repo_utils.py
abstract_ocr/old/seo_utils.py
abstract_ocr/old/text_utils.py
abstract_ocr/old/transcribe_utils.py
abstract_ocr/old/video_utils.py
abstract_ocr/old/audio_utils/__init__.py
abstract_ocr/old/audio_utils/audio_utils.py
abstract_ocr/old/audio_utils/audio_utils_clean.py
abstract_ocr/old/audio_utils/imports.py
abstract_ocr/old/image_utils/__init__.py
abstract_ocr/old/image_utils/image_utils.py
abstract_ocr/old/image_utils/imports.py
abstract_ocr/old/imports/__init__.py
abstract_ocr/old/imports/constants.py
abstract_ocr/old/imports/functions.py
abstract_ocr/old/imports/imports.py
abstract_ocr/old/imports/splitToChunk.py
abstract_ocr/old/ocr_utils/__init__.py
abstract_ocr/old/ocr_utils/imports.py
abstract_ocr/old/ocr_utils/ocr_utils.py
abstract_ocr/old/ocr_utils/tesseract_utils.py
abstract_ocr/old/pdf_utils/__init__.py
abstract_ocr/old/pdf_utils/imports.py
abstract_ocr/old/pdf_utils/pdf_to_text.py
abstract_ocr/old/pdf_utils/pdf_utils.py
abstract_ocr/video_utils/__init__.py
abstract_ocr/video_utils/frame_extract.py
abstract_ocr/video_utils/preprocess.py
abstract_ocr/video_utils/text_extract.py
abstract_ocr-0.0.1.32.dist-info/METADATA
abstract_ocr-0.0.1.32.dist-info/WHEEL
abstract_ocr-0.0.1.32.dist-info/top_level.txt
abstract_ocr-0.0.1.32.dist-info/RECORD
